apydoc/__init__.py
apydoc/gen.py
apydoc/init.py
apydoc/templates/apydoc.json
apydoc-0.0.3.dist-info/METADATA
apydoc-0.0.3.dist-info/RECORD
apydoc-0.0.3.dist-info/WHEEL
apydoc-0.0.3.dist-info/top_level.txt
