Metadata-Version: 2.1
Name: apydoc
Version: 0.0.3
Summary: API documentation generator
Home-page: https://github.com/BlackEarth/apydoc
Author: Sean Harrison
Author-email: sah@blackearth.us
License: LGPL 3.0
Platform: UNKNOWN
Classifier: Development Status :: 1 - Planning
Classifier: Intended Audience :: Developers
Classifier: License :: OSI Approved :: GNU Library or Lesser General Public License (LGPL)
Classifier: Programming Language :: Python :: 3
Provides-Extra: test
Provides-Extra: dev
Provides-Extra: dev
Requires-Dist: twine; extra == 'dev'
Provides-Extra: test
Requires-Dist: nosetests; extra == 'test'
Requires-Dist: coverage; extra == 'test'
